Metadata-Version: 2.4
Name: py2hy
Version: 0.2.0
Summary: Translate Python code to Hy code
Author: Kodi B. Arfer
Project-URL: Source Code, https://github.com/hylang/py2hy
Classifier: License :: OSI Approved :: GNU General Public License v3 or later (GPLv3+)
Classifier: Operating System :: OS Independent
Classifier: Programming Language :: Hy
Requires-Dist: hy>=1.1.0
Requires-Dist: hyrule>=1
Requires-Dist: packaging
Dynamic: author
Dynamic: classifier
Dynamic: description
Dynamic: description-content-type
Dynamic: project-url
Dynamic: requires-dist
Dynamic: summary
